{
  "id": "python-filter",
  "title": "School Filter Bypass - Python",
  "title_ja": "Pythonフィルターバイパス",
  "description": "A Python-based solution for educational network access, enabling students to access legitimate learning resources.",
  "description_ja": "Pythonを使ったサイト規制回避",
  "techStack": [
    "Python",
    "Socket Programming",
    "Network Protocols",
    "Proxy Server",
    "HTTP/HTTPS",
    "サイト規制回避",
    "HTML",
    "replit"
  ],
  "features": [
    {
      "title": "Core Features",
      "title_ja": "主要機能",
      "details": [
        "Bypasses school network filters",
        "Accesses blocked websites",
        "Supports HTTP and HTTPS",
        "Runs on local server",
        "Simple and easy to use"
      ],
      "details_ja": [
        "静的サイトはほとんど見れる",
        "画像処理系も得意",
        "推奨環境はreplit",
        "普通にjsの方が良い。",
        "Google-collaboratで使うには少し難しい。"
      ]
    }
  ],
  "images": [
    "/assets/python-filter/IMG_0385.png",
    "/assets/python-filter/IMG_0384.png"
  ]
} 